diffeqtorch/__init__.py
diffeqtorch/__version__.py
diffeqtorch/diffeqtorch.py
diffeqtorch/install.py
diffeqtorch/logging.py
diffeqtorch/julia/Project.toml
diffeqtorch/julia/precompile.jl
diffeqtorch/julia/sysimage.jl
diffeqtorch-1.0.1.dist-info/LICENSE
diffeqtorch-1.0.1.dist-info/METADATA
diffeqtorch-1.0.1.dist-info/WHEEL
diffeqtorch-1.0.1.dist-info/top_level.txt
diffeqtorch-1.0.1.dist-info/RECORD
