Metadata-Version: 2.1
Name: diffeqtorch
Version: 1.0.1
Summary: DifferentialEquations.jl with PyTorch.
Home-page: https://github.com/sbi-benchmark/diffeqtorch
Author: Jan-Matthis Lueckmann
Author-email: mail@jan-matthis.de
License: MIT
Platform: UNKNOWN
Classifier: Development Status :: 3 - Alpha
Classifier: License :: OSI Approved :: MIT License
Classifier: Programming Language :: Python
Classifier: Programming Language :: Python :: 3
Classifier: Programming Language :: Python :: 3.6
Classifier: Programming Language :: Python :: 3.7
Classifier: Programming Language :: Python :: 3.8
Classifier: Programming Language :: Python :: 3.9
Requires-Python: >=3.6.0, <3.9
Requires-Dist: julia
Requires-Dist: opt-einsum
Requires-Dist: torch
Provides-Extra: dev
Requires-Dist: autoflake ; extra == 'dev'
Requires-Dist: black ; extra == 'dev'
Requires-Dist: flake8 ; extra == 'dev'
Requires-Dist: gitpython ; extra == 'dev'
Requires-Dist: ipdb ; extra == 'dev'
Requires-Dist: isort ; extra == 'dev'
Requires-Dist: nbstripout ; extra == 'dev'
Requires-Dist: pre-commit ; extra == 'dev'
Requires-Dist: pylint ; extra == 'dev'
Requires-Dist: pytest ; extra == 'dev'
Provides-Extra: examples
Requires-Dist: jupyter ; extra == 'examples'
Requires-Dist: matplotlib ; extra == 'examples'
